{
  "accession": "0001437749-25-025772",
  "cik": "0000861842",
  "data": {
    "AccumulatedOtherComprehensiveIncomeLossNetOfTax": {
      "accn": "0001437749-25-025772",
      "context_ref": null,
      "decimals": null,
      "end": "2025-06-30",
      "filed": "2025-08-08",
      "form": "10-Q",
      "fp": "Q2",
      "frame": "CY2025Q2I",
      "fy": 2025,
      "prior": {
        "accn": "0001437749-25-015797",
        "context_ref": null,
        "decimals": null,
        "end": "2024-12-31",
        "filed": "2025-05-09",
        "form": "10-Q",
        "fp": "Q1",
        "frame": null,
        "fy": 2025,
        "start": null,
        "unit": "USD",
        "value": -85607000
      },
      "start": null,
      "unit": "USD",
      "value": -69222000
    },
    "Assets": {
      "accn": "0001437749-25-025772",
      "context_ref": null,
      "decimals": null,
      "end": "2025-06-30",
      "filed": "2025-08-08",
      "form": "10-Q",
      "fp": "Q2",
      "frame": "CY2025Q2I",
      "fy": 2025,
      "prior": {
        "accn": "0001437749-25-015797",
        "context_ref": null,
        "decimals": null,
        "end": "2024-12-31",
        "filed": "2025-05-09",
        "form": "10-Q",
        "fp": "Q1",
        "frame": null,
        "fy": 2025,
        "start": null,
        "unit": "USD",
        "value": 23054681000
      },
      "start": null,
      "unit": "USD",
      "value": 23723847000
    },
    "CommonStockSharesOutstanding": {
      "accn": "0001437749-25-025772",
      "context_ref": null,
      "decimals": null,
      "end": "2025-06-30",
      "filed": "2025-08-08",
      "form": "10-Q",
      "fp": "Q2",
      "frame": "CY2025Q2I",
      "fy": 2025,
      "prior": {
        "accn": "0001437749-25-015797",
        "context_ref": null,
        "decimals": null,
        "end": "2024-12-31",
        "filed": "2025-05-09",
        "form": "10-Q",
        "fp": "Q1",
        "frame": null,
        "fy": 2025,
        "start": null,
        "unit": "shares",
        "value": 70863324
      },
      "start": null,
      "unit": "shares",
      "value": 69343395
    },
    "Deposits": {
      "accn": "0001437749-25-025772",
      "context_ref": null,
      "decimals": null,
      "end": "2025-06-30",
      "filed": "2025-08-08",
      "form": "10-Q",
      "fp": "Q2",
      "frame": "CY2025Q2I",
      "fy": 2025,
      "prior": {
        "accn": "0001437749-25-015797",
        "context_ref": null,
        "decimals": null,
        "end": "2024-12-31",
        "filed": "2025-05-09",
        "form": "10-Q",
        "fp": "Q1",
        "frame": null,
        "fy": 2025,
        "start": null,
        "unit": "USD",
        "value": 19686199000
      },
      "start": null,
      "unit": "USD",
      "value": 20006330000
    },
    "EarningsPerShareDiluted": {
      "accn": "0001437749-25-025772",
      "context_ref": null,
      "decimals": null,
      "end": "2025-06-30",
      "filed": "2025-08-08",
      "form": "10-Q",
      "fp": "Q2",
      "frame": "CY2025Q2",
      "fy": 2025,
      "prior": {
        "accn": "0001437749-25-015797",
        "context_ref": null,
        "decimals": null,
        "end": "2024-03-31",
        "filed": "2025-05-09",
        "form": "10-Q",
        "fp": "Q1",
        "frame": "CY2024Q1",
        "fy": 2025,
        "start": "2024-01-01",
        "unit": "USD/shares",
        "value": 0.98
      },
      "start": "2025-04-01",
      "unit": "USD/shares",
      "value": 1.1
    },
    "Goodwill": {
      "accn": "0001437749-25-025772",
      "context_ref": null,
      "decimals": null,
      "end": "2025-06-30",
      "filed": "2025-08-08",
      "form": "10-Q",
      "fp": "Q2",
      "frame": "CY2025Q2I",
      "fy": 2025,
      "prior": {
        "accn": "0001437749-25-015797",
        "context_ref": null,
        "decimals": null,
        "end": "2024-12-31",
        "filed": "2025-05-09",
        "form": "10-Q",
        "fp": "Q1",
        "frame": null,
        "fy": 2025,
        "start": null,
        "unit": "USD",
        "value": 375696000
      },
      "start": null,
      "unit": "USD",
      "value": 375696000
    },
    "IncomeTaxExpenseBenefit": {
      "accn": "0001437749-25-025772",
      "context_ref": null,
      "decimals": null,
      "end": "2025-06-30",
      "filed": "2025-08-08",
      "form": "10-Q",
      "fp": "Q2",
      "frame": "CY2025Q2",
      "fy": 2025,
      "prior": {
        "accn": "0001437749-25-015797",
        "context_ref": null,
        "decimals": null,
        "end": "2024-03-31",
        "filed": "2025-05-09",
        "form": "10-Q",
        "fp": "Q1",
        "frame": "CY2024Q1",
        "fy": 2025,
        "start": "2024-01-01",
        "unit": "USD",
        "value": 8609000
      },
      "start": "2025-04-01",
      "unit": "USD",
      "value": 18828000
    },
    "IntangibleAssetsNetExcludingGoodwill": {
      "accn": "0001437749-25-025772",
      "context_ref": null,
      "decimals": null,
      "end": "2025-06-30",
      "filed": "2025-08-08",
      "form": "10-Q",
      "fp": "Q2",
      "frame": "CY2025Q2I",
      "fy": 2025,
      "prior": {
        "accn": "0001437749-25-015797",
        "context_ref": null,
        "decimals": null,
        "end": "2024-12-31",
        "filed": "2025-05-09",
        "form": "10-Q",
        "fp": "Q1",
        "frame": null,
        "fy": 2025,
        "start": null,
        "unit": "USD",
        "value": 3335000
      },
      "start": null,
      "unit": "USD",
      "value": 2888000
    },
    "InterestAndDividendIncomeOperating": {
      "accn": "0001437749-25-025772",
      "context_ref": null,
      "decimals": null,
      "end": "2025-06-30",
      "filed": "2025-08-08",
      "form": "10-Q",
      "fp": "Q2",
      "frame": "CY2025Q2",
      "fy": 2025,
      "prior": {
        "accn": "0001437749-25-015797",
        "context_ref": null,
        "decimals": null,
        "end": "2024-03-31",
        "filed": "2025-05-09",
        "form": "10-Q",
        "fp": "Q1",
        "frame": "CY2024Q1",
        "fy": 2025,
        "start": "2024-01-01",
        "unit": "USD",
        "value": 332642000
      },
      "start": "2025-04-01",
      "unit": "USD",
      "value": 322918000
    },
    "InterestIncomeExpenseNet": {
      "accn": "0001437749-25-025772",
      "context_ref": null,
      "decimals": null,
      "end": "2025-06-30",
      "filed": "2025-08-08",
      "form": "10-Q",
      "fp": "Q2",
      "frame": "CY2025Q2",
      "fy": 2025,
      "prior": {
        "accn": "0001437749-25-015797",
        "context_ref": null,
        "decimals": null,
        "end": "2024-03-31",
        "filed": "2025-05-09",
        "form": "10-Q",
        "fp": "Q1",
        "frame": "CY2024Q1",
        "fy": 2025,
        "start": "2024-01-01",
        "unit": "USD",
        "value": 168572000
      },
      "start": "2025-04-01",
      "unit": "USD",
      "value": 181221000
    },
    "NetIncomeLoss": {
      "accn": "0001437749-25-025772",
      "context_ref": null,
      "decimals": null,
      "end": "2025-06-30",
      "filed": "2025-08-08",
      "form": "10-Q",
      "fp": "Q2",
      "frame": "CY2025Q2",
      "fy": 2025,
      "prior": {
        "accn": "0001437749-25-015797",
        "context_ref": null,
        "decimals": null,
        "end": "2024-03-31",
        "filed": "2025-05-09",
        "form": "10-Q",
        "fp": "Q1",
        "frame": "CY2024Q1",
        "fy": 2025,
        "start": "2024-01-01",
        "unit": "USD",
        "value": 71435000
      },
      "start": "2025-04-01",
      "unit": "USD",
      "value": 77450000
    },
    "NoninterestExpense": {
      "accn": "0001437749-25-025772",
      "context_ref": null,
      "decimals": null,
      "end": "2025-06-30",
      "filed": "2025-08-08",
      "form": "10-Q",
      "fp": "Q2",
      "frame": "CY2025Q2",
      "fy": 2025,
      "prior": {
        "accn": "0001437749-25-015797",
        "context_ref": null,
        "decimals": null,
        "end": "2024-03-31",
        "filed": "2025-05-09",
        "form": "10-Q",
        "fp": "Q1",
        "frame": "CY2024Q1",
        "fy": 2025,
        "start": "2024-01-01",
        "unit": "USD",
        "value": 93239000
      },
      "start": "2025-04-01",
      "unit": "USD",
      "value": 89134000
    },
    "NoninterestIncome": {
      "accn": "0001437749-25-025772",
      "context_ref": null,
      "decimals": null,
      "end": "2025-06-30",
      "filed": "2025-08-08",
      "form": "10-Q",
      "fp": "Q2",
      "frame": "CY2025Q2",
      "fy": 2025,
      "prior": {
        "accn": "0001437749-25-015797",
        "context_ref": null,
        "decimals": null,
        "end": "2024-03-31",
        "filed": "2025-05-09",
        "form": "10-Q",
        "fp": "Q1",
        "frame": "CY2024Q1",
        "fy": 2025,
        "start": "2024-01-01",
        "unit": "USD",
        "value": 6611000
      },
      "start": "2025-04-01",
      "unit": "USD",
      "value": 15391000
    },
    "ProvisionForLoanLossesExpensed": {
      "accn": "0001437749-25-025772",
      "context_ref": null,
      "decimals": null,
      "end": "2025-06-30",
      "filed": "2025-08-08",
      "form": "10-Q",
      "fp": "Q2",
      "frame": "CY2025Q2",
      "fy": 2025,
      "prior": {
        "accn": "0001437749-25-015797",
        "context_ref": null,
        "decimals": null,
        "end": "2024-03-31",
        "filed": "2025-05-09",
        "form": "10-Q",
        "fp": "Q1",
        "frame": "CY2024Q1",
        "fy": 2025,
        "start": "2024-01-01",
        "unit": "USD",
        "value": 1900000
      },
      "start": "2025-04-01",
      "unit": "USD",
      "value": 11200000
    },
    "StockholdersEquity": {
      "accn": "0001437749-25-025772",
      "context_ref": null,
      "decimals": null,
      "end": "2025-06-30",
      "filed": "2025-08-08",
      "form": "10-Q",
      "fp": "Q2",
      "frame": "CY2025Q2I",
      "fy": 2025,
      "prior": {
        "accn": "0001437749-25-015797",
        "context_ref": null,
        "decimals": null,
        "end": "2023-12-31",
        "filed": "2025-05-09",
        "form": "10-Q",
        "fp": "Q1",
        "frame": null,
        "fy": 2025,
        "start": null,
        "unit": "USD",
        "value": 2736575000
      },
      "start": null,
      "unit": "USD",
      "value": 2886295000
    }
  },
  "fetch_timestamp": "2025-10-20T02:28:52Z",
  "filing_date": "2025-08-08",
  "form_type": "10-Q",
  "period_end": "2025-06-30",
  "primary_document": "caty20250630_10q.htm",
  "prior_accession": "0001437749-25-015797",
  "prior_period_end": "2025-03-31",
  "source": "SEC EDGAR",
  "ticker": "CATY"
}
